pytrad/__init__.py
pytrad/graph/AdjacencyConfusion.py
pytrad/graph/ArrowConfusion.py
pytrad/graph/Dag.py
pytrad/graph/Edge.py
pytrad/graph/Edges.py
pytrad/graph/Endpoint.py
pytrad/graph/GeneralGraph.py
pytrad/graph/Graph.py
pytrad/graph/GraphClass.py
pytrad/graph/GraphNode.py
pytrad/graph/Node.py
pytrad/graph/NodeType.py
pytrad/graph/NodeVariableType.py
pytrad/graph/SHD.py
pytrad/graph/__init__.py
pytrad/score/LocalScoreFunction.py
pytrad/score/__init__.py
pytrad/search/__init__.py
pytrad/search/ConstraintBased/CDNOD.py
pytrad/search/ConstraintBased/FCI.py
pytrad/search/ConstraintBased/PC.py
pytrad/search/ConstraintBased/__init__.py
pytrad/search/FCMBased/__init__.py
pytrad/search/FCMBased/ANM/ANM.py
pytrad/search/FCMBased/ANM/__init__.py
pytrad/search/FCMBased/PNL/PNL.py
pytrad/search/FCMBased/PNL/__init__.py
pytrad/search/FCMBased/lingam/CAMUV.py
pytrad/search/FCMBased/lingam/__init__.py
pytrad/search/FCMBased/lingam/base.py
pytrad/search/FCMBased/lingam/bootstrap.py
pytrad/search/FCMBased/lingam/bottom_up_parce_lingam.py
pytrad/search/FCMBased/lingam/causal_effect.py
pytrad/search/FCMBased/lingam/direct_lingam.py
pytrad/search/FCMBased/lingam/hsic.py
pytrad/search/FCMBased/lingam/hsic2.py
pytrad/search/FCMBased/lingam/ica_lingam.py
pytrad/search/FCMBased/lingam/longitudinal_lingam.py
pytrad/search/FCMBased/lingam/multi_group_direct_lingam.py
pytrad/search/FCMBased/lingam/rcd.py
pytrad/search/FCMBased/lingam/var_lingam.py
pytrad/search/FCMBased/lingam/varma_lingam.py
pytrad/search/FCMBased/lingam/utils/__init__.py
pytrad/search/Granger/Granger.py
pytrad/search/Granger/__init__.py
pytrad/search/HiddenCausal/__init__.py
pytrad/search/HiddenCausal/GIN/GIN.py
pytrad/search/HiddenCausal/GIN/__init__.py
pytrad/search/ScoreBased/ExactSearch.py
pytrad/search/ScoreBased/GES.py
pytrad/search/ScoreBased/__init__.py
pytrad/utils/DAG2CPDAG.py
pytrad/utils/DAG2PAG.py
pytrad/utils/GESUtils.py
pytrad/utils/GraphUtils.py
pytrad/utils/MECCheck.py
pytrad/utils/PDAG2DAG.py
Pytrad-0.1.1.5.dist-info/METADATA
Pytrad-0.1.1.5.dist-info/WHEEL
Pytrad-0.1.1.5.dist-info/top_level.txt
Pytrad-0.1.1.5.dist-info/RECORD
