Metadata-Version: 2.1
Name: Pytrad
Version: 0.1.1.5
Summary: Pytrad Python Package
Home-page: https://github.com/cmu-phil/pytrad
Author: 
License: UNKNOWN
Platform: UNKNOWN
Classifier: Programming Language :: Python :: 3
Classifier: License :: OSI Approved :: MIT License
Classifier: Operating System :: OS Independent
Requires-Python: >=3.6
Requires-Dist: numpy
Requires-Dist: scipy
Requires-Dist: scikit-learn
Requires-Dist: graphviz
Requires-Dist: statsmodels
Requires-Dist: pandas
Requires-Dist: matplotlib
Requires-Dist: networkx
Requires-Dist: pydot
